proxmox_pci_switcher/__init__.py
proxmox_pci_switcher/proxmox_pci_switcher.py
proxmox_pci_switcher/ui/__init__.py
proxmox_pci_switcher/ui/logo.png
proxmox_pci_switcher/ui/main.kv
proxmox_pci_switcher/ui/main.py
proxmox_pci_switcher-0.15.11.dist-info/LICENSE
proxmox_pci_switcher-0.15.11.dist-info/METADATA
proxmox_pci_switcher-0.15.11.dist-info/WHEEL
proxmox_pci_switcher-0.15.11.dist-info/entry_points.txt
proxmox_pci_switcher-0.15.11.dist-info/top_level.txt
proxmox_pci_switcher-0.15.11.dist-info/RECORD
