Metadata-Version: 2.1
Name: proxmox-pci-switcher
Version: 0.15.11
Summary: Switch among Guest VMs organized by Resource Pool
Home-page: https://github.com/rosineygp/proxmox-pci-switcher
Author: Rosiney Gomes Pereira
Author-email: rosiney.gp@gmail.com
License: MIT
Platform: UNKNOWN
Classifier: Intended Audience :: Developers
Classifier: Natural Language :: English
Classifier: Topic :: System :: Networking
Requires-Python: >=3.6
License-File: LICENSE
Requires-Dist: proxmoxer ==2.0.1
Requires-Dist: requests ==2.31.0
Requires-Dist: paramiko ==3.4.0
Requires-Dist: argh ==0.26.2
Requires-Dist: PyYAML ==6.0.1
Requires-Dist: tabulate ==0.9.0
Requires-Dist: Kivy ==2.3.0
Requires-Dist: kivymd ==0.104.2
